tests
stexp
