Metadata-Version: 1.0
Name: stexproject
Version: 0.0.5
Summary: It's just a demonstration
Home-page: http://packages.python.org/stexproject
Author: ijiaruo
Author-email: ijiaruo@gmail.com
License: GPL
Keywords: example documentation tutorial
Platform: UNKNOWN
Classifier: Development Status :: 3 - Alpha
Classifier: Topic :: Utilities
Classifier: License :: OSI Approved :: GNU General Public License (GPL)
